{
  "schema": "active-run-v1",
  "updated_at": "2026-07-16",
  "status": "search25_retry4_prepared_not_triggered",
  "active_run": null,
  "do_not_duplicate_run_id": 29453747947,
  "last_completed_run": {
    "workflow": "smart-search-24-defect-graft",
    "run_id": 29357369876,
    "run_url": "https://github.com/Grisha-Pochuev/minimum-link-covering-trail-4x4x4/actions/runs/29357369876",
    "aggregate_status": "success_strict",
    "full_status": "success_strict_20_of_20",
    "best_ordered_covered_count": 62,
    "ordered_63_trails": 0,
    "ordered_64_trails": 0
  },
  "step2_handoff": {
    "workflow_name": "smart-search-25-core-valley",
    "hypothesis": "atomic paired core-valley replacement with exact finite contact-span scoring",
    "engine_language": "C++20",
    "plateau62_closed_state_count": 43,
    "common_core_lines": 17,
    "corebreak61_seed_count": 641,
    "numeric_frontier_after_local_experiments": 62
  },
  "step3_implementation": {
    "workflow_path": ".github/workflows/smart-search-25-core-valley.yml",
    "runtime_archive": "data/search25_runtime.tar.gz",
    "runtime_archive_sha256": "96f974b47308838fae1e2dadf9ddb81860345afc05ddb13db329af80f98cec1c",
    "full_profile": {
      "search_seconds": 20400,
      "timeout_minutes": 359,
      "shards": 20,
      "workers_per_shard": 4,
      "checkpoint_seconds": 600,
      "minimum_headroom_seconds": 900
    },
    "input_validation": "all 684 rows are checked semantically; plateau intersection must equal common17; every valley row must break the core; 51 missing-triple classes required",
    "preflight_diagnostics_artifact": "smart-search-25-preflight-diagnostics",
    "triggered": false
  },
  "technical_attempts": [
    {"attempt": 1, "run_id": 29452854208, "launch_commit": "6ac6cc0c2798423898145964dc15d6662706bb57", "failure_step": "shared preflight", "smoke": "not_started", "full": "not_started"},
    {"attempt": 2, "run_id": 29453335991, "launch_commit": "cb67f63a81b6fc6347573d4f300b1ee623a2ff69", "failure_step": "outer input bundle hash gate", "smoke": "not_started", "full": "not_started"},
    {"attempt": 3, "run_id": 29453747947, "launch_commit": "011eab49b5aa0a22f522f0c46a2220bdcc7602ce", "failure_step": "shared 20-mode preflight", "smoke": "not_started", "full": "not_started"}
  ],
  "next_action": "Publish semantic-input validation and durable preflight diagnostics, then trigger retry 4 exactly once and inspect the unique new run."
}
