{
  "candidate_id": "mlct22-order-5c31614d2aeaa2aa",
  "coordinate_scale": 2,
  "covered_count": 44,
  "grid_points": 64,
  "links": 22,
  "missing": [[0,0,3],[0,3,0],[0,3,1],[1,0,0],[1,0,1],[1,3,3],[2,0,0],[2,0,1],[2,0,2],[2,3,1],[2,3,2],[2,3,3],[3,0,1],[3,0,2],[3,0,3],[3,1,3],[3,2,0],[3,3,0],[3,3,1],[3,3,2]],
  "missing_count": 20,
  "mode": "one_two_line_mutation",
  "ordered_candidate_key_sha256": "5c31614d2aeaa2aa6658c9e291ebcce2c0512c3a3378dbf56c05316a2a9cab50",
  "parameters": {
    "beam_width": 512,
    "box_max": 4,
    "box_min": -1,
    "branch_limit": 5,
    "candidate_lines": 3000,
    "max_mutations": 2,
    "min_line_cover": 2,
    "seconds": 21000,
    "seed": 20260718,
    "shard": 7,
    "shards": 20,
    "start_limit": 22,
    "workers": 4
  },
  "schema": "contact-aware-ordering-result-v1-compact",
  "score": 4422400,
  "source_artifact": "order-cover64-stitch-22-shard-7",
  "source_file_in_artifact": "collected/order_from_cover64_best_shard_7.json",
  "source_run_id": 28875314204,
  "source_scaffold_file": "candidates/line-set-additions-run28825060197-cover64-stitch.jsonl",
  "source_scaffold_id": "mlct22-lineset-03bc99e72246b78c",
  "source_shard": 7,
  "source_workflow": "smart-search-18-order-from-cover64-stitch",
  "status": "full_length_ordered_chain",
  "vertices2": [[6,2,0],[0,2,0],[0,2,6],[4,2,6],[4,0,6],[4,6,0],[4,4,0],[0,4,0],[0,4,6],[6,4,6],[6,2,4],[6,4,2],[6,2,2],[6,6,6],[0,0,0],[0,0,4],[2,0,4],[2,0,6],[2,6,0],[2,6,4],[0,6,4],[0,6,6],[6,0,0]],
  "weak_links": 0,
  "note": "Compact copy of the best diagnostic ordered-chain reconstruction. Full raw artifact is preserved in order-cover64-stitch-run-summary.zip. This is below the standing 60/64 ordered-trail frontier."
}
